conductor/__init__.py
conductor/__main__.py
conductor/cli.py
conductor/conductor.py
conductor/agents/__init__.py
conductor/agents/base.py
conductor/agents/executor.py
conductor/agents/planner.py
conductor/agents/repair.py
conductor/agents/reviewer.py
conductor/agents/verifier.py
conductor/config/__init__.py
conductor/config/client.py
conductor/config/models.py
conductor/db/__init__.py
conductor/db/models.py
conductor/db/repository.py
conductor/db/schema.sql
conductor/exploration/__init__.py
conductor/exploration/engine.py
conductor/exploration/replay.py
conductor/handoff/__init__.py
conductor/handoff/adapter.py
conductor/handoff/confidence.py
conductor/handoff/explainer.py
conductor/handoff/provenance.py
conductor/handoff/schema.py
conductor/mcp/__init__.py
conductor/mcp/discovery.py
conductor/mcp/recorder.py
conductor/mcp/router.py
conductor/memory/__init__.py
conductor/memory/store.py
conductor/policy/__init__.py
conductor/policy/engine.py
conductor/policy/loader.py
conductor_runtime-3.0.4.dist-info/licenses/LICENSE
conductor_runtime-3.0.4.dist-info/METADATA
conductor_runtime-3.0.4.dist-info/WHEEL
conductor_runtime-3.0.4.dist-info/entry_points.txt
conductor_runtime-3.0.4.dist-info/top_level.txt
conductor_runtime-3.0.4.dist-info/RECORD
