Metadata-Version: 2.4
Name: conductor-runtime
Version: 3.0.4
Summary: Autonomous, Policy-Governed, Learning Orchestration Runtime for AI Agents
Author: Conductor Team
License: MIT
Project-URL: Homepage, https://github.com/conductor-runtime/conductor
Project-URL: Documentation, https://github.com/conductor-runtime/conductor#readme
Project-URL: Repository, https://github.com/conductor-runtime/conductor
Project-URL: Changelog, https://github.com/conductor-runtime/conductor/blob/main/CHANGELOG.md
Keywords: orchestration,autonomous,ai,agents,llm,automation,conductor,handoff
Classifier: Development Status :: 4 - Beta
Classifier: Intended Audience :: Developers
Classifier: License :: OSI Approved :: MIT License
Classifier: Programming Language :: Python :: 3
Classifier: Programming Language :: Python :: 3.11
Classifier: Programming Language :: Python :: 3.12
Classifier: Programming Language :: Python :: 3.13
Classifier: Programming Language :: Python :: 3.14
Classifier: Topic :: Software Development :: Libraries :: Python Modules
Classifier: Topic :: Scientific/Engineering :: Artificial Intelligence
Requires-Python: >=3.11
License-File: LICENSE
Requires-Dist: openai>=1.0.0
Requires-Dist: click>=8.0.0
Requires-Dist: python-dotenv>=1.0.0
Requires-Dist: pydantic>=2.0.0
Requires-Dist: PyYAML>=6.0.0
Provides-Extra: dev
Requires-Dist: pytest>=7.0.0; extra == "dev"
Requires-Dist: pytest-asyncio>=0.21.0; extra == "dev"
Dynamic: license-file
